slim_trees/__init__.py
slim_trees/compression_utils.py
slim_trees/lgbm_booster.py
slim_trees/pickling.py
slim_trees/py.typed
slim_trees/sklearn_tree.py
slim_trees/utils.py
slim_trees-0.2.14.dist-info/METADATA
slim_trees-0.2.14.dist-info/WHEEL
slim_trees-0.2.14.dist-info/licenses/LICENSE
slim_trees-0.2.14.dist-info/RECORD
