Metadata-Version: 2.4
Name: slim-trees
Version: 0.2.14
Summary: A python package for efficient pickling of ML models.
Project-URL: Homepage, https://github.com/quantco/slim-trees
Author-email: Pavel Zwerschke <pavel.zwerschke@quantco.com>
License: MIT License
License-File: LICENSE
Classifier: Programming Language :: Python :: 3
Classifier: Programming Language :: Python :: 3.8
Classifier: Programming Language :: Python :: 3.9
Classifier: Programming Language :: Python :: 3.10
Classifier: Programming Language :: Python :: 3.11
Classifier: Programming Language :: Python :: 3.12
Requires-Python: >=3.8
Requires-Dist: numpy<3,>=1
Provides-Extra: lightgbm
Requires-Dist: lightgbm<4.4,>=3.2; extra == 'lightgbm'
Provides-Extra: scikit-learn
Requires-Dist: scikit-learn<1.6,>=1.1.0; extra == 'scikit-learn'
